README.md
setup.py
MfP3/__init__.py
MfP3.egg-info/PKG-INFO
MfP3.egg-info/SOURCES.txt
MfP3.egg-info/dependency_links.txt
MfP3.egg-info/requires.txt
MfP3.egg-info/top_level.txt